odoo9_addon_mrp_repair_refurbish-9.0.1.0.1.99.dev6-nspkg.pth
odoo_addons/mrp_repair_refurbish/README.rst
odoo_addons/mrp_repair_refurbish/__init__.py
odoo_addons/mrp_repair_refurbish/__openerp__.py
odoo_addons/mrp_repair_refurbish/data/stock_data.xml
odoo_addons/mrp_repair_refurbish/i18n/mrp_repair_refurbish.pot
odoo_addons/mrp_repair_refurbish/models/__init__.py
odoo_addons/mrp_repair_refurbish/models/mrp_repair.py
odoo_addons/mrp_repair_refurbish/models/product_product.py
odoo_addons/mrp_repair_refurbish/models/product_template.py
odoo_addons/mrp_repair_refurbish/static/description/icon.png
odoo_addons/mrp_repair_refurbish/views/mrp_repair_view.xml
odoo_addons/mrp_repair_refurbish/views/product_product_view.xml
odoo_addons/mrp_repair_refurbish/views/product_template_view.xml
odoo9_addon_mrp_repair_refurbish-9.0.1.0.1.99.dev6.dist-info/METADATA
odoo9_addon_mrp_repair_refurbish-9.0.1.0.1.99.dev6.dist-info/WHEEL
odoo9_addon_mrp_repair_refurbish-9.0.1.0.1.99.dev6.dist-info/namespace_packages.txt
odoo9_addon_mrp_repair_refurbish-9.0.1.0.1.99.dev6.dist-info/top_level.txt
odoo9_addon_mrp_repair_refurbish-9.0.1.0.1.99.dev6.dist-info/RECORD
